{"_cached_at": "2026-02-09T12:56:27.136703", "_endpoint": "fixtures/statistics", "_params": {"fixture": 1379172}, "data": {"get": "fixtures/statistics", "parameters": {"fixture": "1379172"}, "errors": [], "results": 2, "paging": {"current": 1, "total": 1}, "response": [{"team": {"id": 44, "name": "Burnley", "logo": "https://media.api-sports.io/football/teams/44.png"}, "statistics": [{"type": "Shots on Goal", "value": 1}, {"type": "Shots off Goal", "value": 1}, {"type": "Total Shots", "value": 7}, {"type": "Blocked Shots", "value": 5}, {"type": "Shots insidebox", "value": 6}, {"type": "Shots outsidebox", "value": 1}, {"type": "Fouls", "value": 9}, {"type": "Corner Kicks", "value": 2}, {"type": "Offsides", "value": 3}, {"type": "Ball Possession", "value": "35%"}, {"type": "Yellow Cards", "value": 2}, {"type": "Red Cards", "value": null}, {"type": "Goalkeeper Saves", "value": 6}, {"type": "Total passes", "value": 315}, {"type": "Passes accurate", "value": 240}, {"type": "Passes %", "value": "76%"}, {"type": "expected_goals", "value": "0.24"}, {"type": "goals_prevented", "value": -1}]}, {"team": {"id": 33, "name": "Manchester United", "logo": "https://media.api-sports.io/football/teams/33.png"}, "statistics": [{"type": "Shots on Goal", "value": 10}, {"type": "Shots off Goal", "value": 13}, {"type": "Total Shots", "value": 30}, {"type": "Blocked Shots", "value": 7}, {"type": "Shots insidebox", "value": 21}, {"type": "Shots outsidebox", "value": 9}, {"type": "Fouls", "value": 8}, {"type": "Corner Kicks", "value": 6}, {"type": "Offsides", "value": 0}, {"type": "Ball Possession", "value": "65%"}, {"type": "Yellow Cards", "value": 0}, {"type": "Red Cards", "value": null}, {"type": "Goalkeeper Saves", "value": 0}, {"type": "Total passes", "value": 593}, {"type": "Passes accurate", "value": 519}, {"type": "Passes %", "value": "88%"}, {"type": "expected_goals", "value": "2.55"}, {"type": "goals_prevented", "value": -1}]}]}}