{"_cached_at": "2026-02-09T21:44:15.034771", "_endpoint": "injuries", "_params": {"fixture": 1378095}, "data": {"get": "injuries", "parameters": {"fixture": "1378095"}, "errors": [], "results": 7, "paging": {"current": 1, "total": 1}, "response": [{"player": {"id": 30853, "name": "K. Bonifazi", "photo": "https://media.api-sports.io/football/players/30853.png", "type": "Missing Fixture", "reason": "Inactive"}, "team": {"id": 500, "name": "Bologna", "logo": "https://media.api-sports.io/football/teams/500.png"}, "fixture": {"id": 1378095, "timezone": "UTC", "date": "2026-02-08T11:30:00+00:00", "timestamp": 1770550200}, "league": {"id": 135, "season": 2025, "name": "Serie A", "country": "Italy", "logo": "https://media.api-sports.io/football/leagues/135.png", "flag": "https://media.api-sports.io/flags/it.svg"}}, {"player": {"id": 30498, "name": "L. De Silvestri", "photo": "https://media.api-sports.io/football/players/30498.png", "type": "Missing Fixture", "reason": "Abdominal strain"}, "team": {"id": 500, "name": "Bologna", "logo": "https://media.api-sports.io/football/teams/500.png"}, "fixture": {"id": 1378095, "timezone": "UTC", "date": "2026-02-08T11:30:00+00:00", "timestamp": 1770550200}, "league": {"id": 135, "season": 2025, "name": "Serie A", "country": "Italy", "logo": "https://media.api-sports.io/football/leagues/135.png", "flag": "https://media.api-sports.io/flags/it.svg"}}, {"player": {"id": 6409, "name": "N. Estevez", "photo": "https://media.api-sports.io/football/players/6409.png", "type": "Missing Fixture", "reason": "Knee Injury"}, "team": {"id": 523, "name": "Parma", "logo": "https://media.api-sports.io/football/teams/523.png"}, "fixture": {"id": 1378095, "timezone": "UTC", "date": "2026-02-08T11:30:00+00:00", "timestamp": 1770550200}, "league": {"id": 135, "season": 2025, "name": "Serie A", "country": "Italy", "logo": "https://media.api-sports.io/football/leagues/135.png", "flag": "https://media.api-sports.io/flags/it.svg"}}, {"player": {"id": 292543, "name": "M. Frigan", "photo": "https://media.api-sports.io/football/players/292543.png", "type": "Missing Fixture", "reason": "Knee Injury"}, "team": {"id": 523, "name": "Parma", "logo": "https://media.api-sports.io/football/teams/523.png"}, "fixture": {"id": 1378095, "timezone": "UTC", "date": "2026-02-08T11:30:00+00:00", "timestamp": 1770550200}, "league": {"id": 135, "season": 2025, "name": "Serie A", "country": "Italy", "logo": "https://media.api-sports.io/football/leagues/135.png", "flag": "https://media.api-sports.io/flags/it.svg"}}, {"player": {"id": 203483, "name": "A. Ndiaye", "photo": "https://media.api-sports.io/football/players/203483.png", "type": "Missing Fixture", "reason": "Groin Injury"}, "team": {"id": 523, "name": "Parma", "logo": "https://media.api-sports.io/football/teams/523.png"}, "fixture": {"id": 1378095, "timezone": "UTC", "date": "2026-02-08T11:30:00+00:00", "timestamp": 1770550200}, "league": {"id": 135, "season": 2025, "name": "Serie A", "country": "Italy", "logo": "https://media.api-sports.io/football/leagues/135.png", "flag": "https://media.api-sports.io/flags/it.svg"}}, {"player": {"id": 199578, "name": "Z. Suzuki", "photo": "https://media.api-sports.io/football/players/199578.png", "type": "Missing Fixture", "reason": "Finger Injury"}, "team": {"id": 523, "name": "Parma", "logo": "https://media.api-sports.io/football/teams/523.png"}, "fixture": {"id": 1378095, "timezone": "UTC", "date": "2026-02-08T11:30:00+00:00", "timestamp": 1770550200}, "league": {"id": 135, "season": 2025, "name": "Serie A", "country": "Italy", "logo": "https://media.api-sports.io/football/leagues/135.png", "flag": "https://media.api-sports.io/flags/it.svg"}}, {"player": {"id": 6221, "name": "L. Valenti", "photo": "https://media.api-sports.io/football/players/6221.png", "type": "Missing Fixture", "reason": "Muscle Injury"}, "team": {"id": 523, "name": "Parma", "logo": "https://media.api-sports.io/football/teams/523.png"}, "fixture": {"id": 1378095, "timezone": "UTC", "date": "2026-02-08T11:30:00+00:00", "timestamp": 1770550200}, "league": {"id": 135, "season": 2025, "name": "Serie A", "country": "Italy", "logo": "https://media.api-sports.io/football/leagues/135.png", "flag": "https://media.api-sports.io/flags/it.svg"}}]}}